llmtrace/__init__.py
llmtrace/_logging.py
llmtrace/plugins.py
llmtrace/cli/cli.py
llmtrace/core/core.py
llmtrace/dashboard/app.py
llmtrace/dashboard/templates/index.html
llmtrace/evaluation/evaluation.py
llmtrace/feedback/api.py
llmtrace/instrumentation/base.py
llmtrace/instrumentation/huggingface.py
llmtrace/instrumentation/langchain.py
llmtrace/instrumentation/openai.py
llmtrace/storage/__init__.py
llmtrace/storage/backends.py
llmtrace/storage/postgresql.py
llmtrace/storage/sqlite.py
llmtrace/tracing/models.py
llmtrace-0.1.4.dist-info/licenses/LICENSE-THIRD-PARTY.md
llmtrace-0.1.4.dist-info/METADATA
llmtrace-0.1.4.dist-info/WHEEL
llmtrace-0.1.4.dist-info/entry_points.txt
llmtrace-0.1.4.dist-info/top_level.txt
llmtrace-0.1.4.dist-info/RECORD
